spark_data_test/__init__.py
spark_data_test/constants/__init__.py
spark_data_test/constants/common_constants.py
spark_data_test/entities/__init__.py
spark_data_test/entities/config.py
spark_data_test/jobs/__init__.py
spark_data_test/jobs/comparison_job.py
spark_data_test/utils/__init__.py
spark_data_test/utils/config_reader.py
spark_data_test/utils/io_utils.py
spark_data_test/utils/spark_utils.py
spark_data_test-0.1.2.dist-info/licenses/LICENSE
tests/__init__.py
tests/test_comparison_job.py
tests/test_config_reader.py
spark_data_test-0.1.2.dist-info/METADATA
spark_data_test-0.1.2.dist-info/WHEEL
spark_data_test-0.1.2.dist-info/top_level.txt
spark_data_test-0.1.2.dist-info/RECORD
