Metadata-Version: 2.4
Name: spark_data_test
Version: 0.1.2
Summary: A library for validating and comparing datasets in Spark using PySpark.
Author: Jafeer Ali
Author-email: jafeeralin@gmail.com
License: MIT
Requires-Python: >=3.7
License-File: LICENSE
Requires-Dist: dacite>=v1.9.2
Requires-Dist: pyspark==3.5.6
Provides-Extra: dev
Requires-Dist: numpy==1.26.4; extra == "dev"
Requires-Dist: pytest>=5; extra == "dev"
Requires-Dist: pytest-cov; extra == "dev"
Requires-Dist: pandas==2.2.2; extra == "dev"
Requires-Dist: pyarrow==14.0.2; extra == "dev"
Dynamic: author
Dynamic: author-email
Dynamic: description
Dynamic: description-content-type
Dynamic: license
Dynamic: license-file
Dynamic: provides-extra
Dynamic: requires-dist
Dynamic: requires-python
Dynamic: summary
